package_readme.md
wandb/__init__.py
wandb/__main__.py
wandb/_globals.py
wandb/data_types.py
wandb/env.py
wandb/jupyter.py
wandb/magic.py
wandb/py.typed
wandb/trigger.py
wandb/util.py
wandb/viz.py
wandb/wandb_agent.py
wandb/wandb_controller.py
wandb/wandb_run.py
wandb/wandb_torch.py
wandb/agents/__init__.py
wandb/agents/pyagent.py
wandb/analytics/__init__.py
wandb/analytics/sentry.py
wandb/apis/__init__.py
wandb/apis/attrs.py
wandb/apis/internal.py
wandb/apis/normalize.py
wandb/apis/paginator.py
wandb/apis/importers/__init__.py
wandb/apis/importers/mlflow.py
wandb/apis/importers/validation.py
wandb/apis/importers/wandb.py
wandb/apis/importers/internals/internal.py
wandb/apis/importers/internals/protocols.py
wandb/apis/importers/internals/util.py
wandb/apis/public/__init__.py
wandb/apis/public/api.py
wandb/apis/public/artifacts.py
wandb/apis/public/const.py
wandb/apis/public/files.py
wandb/apis/public/history.py
wandb/apis/public/jobs.py
wandb/apis/public/projects.py
wandb/apis/public/query_generator.py
wandb/apis/public/reports.py
wandb/apis/public/runs.py
wandb/apis/public/sweeps.py
wandb/apis/public/teams.py
wandb/apis/public/users.py
wandb/apis/reports/__init__.py
wandb/apis/reports/v1/__init__.py
wandb/apis/reports/v2/__init__.py
wandb/apis/workspaces/__init__.py
wandb/beta/workflows.py
wandb/bin/nvidia_gpu_stats
wandb/bin/wandb-core
wandb/cli/__init__.py
wandb/cli/cli.py
wandb/docker/__init__.py
wandb/docker/auth.py
wandb/docker/wandb-entrypoint.sh
wandb/docker/www_authenticate.py
wandb/errors/__init__.py
wandb/errors/term.py
wandb/errors/util.py
wandb/filesync/__init__.py
wandb/filesync/dir_watcher.py
wandb/filesync/stats.py
wandb/filesync/step_checksum.py
wandb/filesync/step_prepare.py
wandb/filesync/step_upload.py
wandb/filesync/upload_job.py
wandb/integration/__init__.py
wandb/integration/magic.py
wandb/integration/catboost/__init__.py
wandb/integration/catboost/catboost.py
wandb/integration/cohere/__init__.py
wandb/integration/cohere/cohere.py
wandb_zc-0.17.7.dev1.dist-info/METADATA
wandb_zc-0.17.7.dev1.dist-info/WHEEL
wandb_zc-0.17.7.dev1.dist-info/entry_points.txt
wandb_zc-0.17.7.dev1.dist-info/licenses/LICENSE
wandb_zc-0.17.7.dev1.dist-info/RECORD
