Metadata-Version: 2.3
Name: wandb-zc
Version: 0.17.7.dev1
Summary: A CLI and library for interacting with the Weights & Biases API.
Project-URL: Source, https://github.com/wandb/wandb
Project-URL: Bug Reports, https://github.com/wandb/wandb/issues
Project-URL: Documentation, https://docs.wandb.ai/
Author-email: Weights & Biases <support@wandb.com>
License: MIT License
License-File: LICENSE
Classifier: Development Status :: 5 - Production/Stable
Classifier: Intended Audience :: Developers
Classifier: Intended Audience :: Science/Research
Classifier: License :: OSI Approved :: MIT License
Classifier: Natural Language :: English
Classifier: Programming Language :: Python :: 3
Classifier: Programming Language :: Python :: 3 :: Only
Classifier: Programming Language :: Python :: 3.7
Classifier: Programming Language :: Python :: 3.8
Classifier: Programming Language :: Python :: 3.9
Classifier: Programming Language :: Python :: 3.10
Classifier: Programming Language :: Python :: 3.11
Classifier: Programming Language :: Python :: 3.12
Classifier: Topic :: Scientific/Engineering :: Artificial Intelligence
Classifier: Topic :: Software Development :: Libraries :: Python Modules
Classifier: Topic :: System :: Logging
Classifier: Topic :: System :: Monitoring
Requires-Python: >=3.7
Requires-Dist: click!=8.0.0,>=7.1
Requires-Dist: docker-pycreds>=0.4.0
Requires-Dist: gitpython!=3.1.29,>=1.0.0
Requires-Dist: platformdirs
Requires-Dist: protobuf!=4.21.0,<6,>=3.12.0; python_version < '3.9' and sys_platform == 'linux'
Requires-Dist: protobuf!=4.21.0,<6,>=3.15.0; python_version == '3.9' and sys_platform == 'linux'
Requires-Dist: protobuf!=4.21.0,<6,>=3.19.0; python_version > '3.9' and sys_platform == 'linux'
Requires-Dist: protobuf!=4.21.0,<6,>=3.19.0; sys_platform != 'linux'
Requires-Dist: psutil>=5.0.0
Requires-Dist: pyyaml
Requires-Dist: requests<3,>=2.0.0
Requires-Dist: sentry-sdk>=1.0.0
Requires-Dist: setproctitle
Requires-Dist: setuptools
Requires-Dist: typing-extensions; python_version < '3.10'
Provides-Extra: aws
Requires-Dist: boto3; extra == 'aws'
Provides-Extra: azure
Requires-Dist: azure-identity; extra == 'azure'
Requires-Dist: azure-storage-blob; extra == 'azure'
Provides-Extra: gcp
Requires-Dist: google-cloud-storage; extra == 'gcp'
Provides-Extra: importers
Requires-Dist: filelock; extra == 'importers'
Requires-Dist: mlflow; extra == 'importers'
Requires-Dist: polars<=1.2.1; extra == 'importers'
Requires-Dist: rich; extra == 'importers'
Requires-Dist: tenacity; extra == 'importers'
Provides-Extra: kubeflow
Requires-Dist: google-cloud-storage; extra == 'kubeflow'
Requires-Dist: kubernetes; extra == 'kubeflow'
Requires-Dist: minio; extra == 'kubeflow'
Requires-Dist: sh; extra == 'kubeflow'
Provides-Extra: launch
Requires-Dist: awscli; extra == 'launch'
Requires-Dist: azure-containerregistry; extra == 'launch'
Requires-Dist: azure-identity; extra == 'launch'
Requires-Dist: azure-storage-blob; extra == 'launch'
Requires-Dist: boto3; extra == 'launch'
Requires-Dist: botocore; extra == 'launch'
Requires-Dist: chardet; extra == 'launch'
Requires-Dist: google-auth; extra == 'launch'
Requires-Dist: google-cloud-aiplatform; extra == 'launch'
Requires-Dist: google-cloud-artifact-registry; extra == 'launch'
Requires-Dist: google-cloud-compute; extra == 'launch'
Requires-Dist: google-cloud-storage; extra == 'launch'
Requires-Dist: iso8601; extra == 'launch'
Requires-Dist: jsonschema; extra == 'launch'
Requires-Dist: kubernetes; extra == 'launch'
Requires-Dist: kubernetes-asyncio; extra == 'launch'
Requires-Dist: nbconvert; extra == 'launch'
Requires-Dist: nbformat; extra == 'launch'
Requires-Dist: optuna; extra == 'launch'
Requires-Dist: pydantic; extra == 'launch'
Requires-Dist: pyyaml>=6.0.0; extra == 'launch'
Requires-Dist: tomli; extra == 'launch'
Requires-Dist: typing-extensions; extra == 'launch'
Provides-Extra: media
Requires-Dist: bokeh; extra == 'media'
Requires-Dist: moviepy; extra == 'media'
Requires-Dist: numpy; extra == 'media'
Requires-Dist: pillow; extra == 'media'
Requires-Dist: plotly>=5.18.0; extra == 'media'
Requires-Dist: rdkit-pypi; extra == 'media'
Requires-Dist: soundfile; extra == 'media'
Provides-Extra: models
Requires-Dist: cloudpickle; extra == 'models'
Provides-Extra: perf
Requires-Dist: orjson; extra == 'perf'
Provides-Extra: sweeps
Requires-Dist: sweeps>=0.2.0; extra == 'sweeps'
Provides-Extra: workspaces
Requires-Dist: wandb-workspaces; extra == 'workspaces'
